mgrid/__init__.py
mgrid/api.py
mgrid/cli.py
mgrid/geometry.py
mgrid/io.py
mgrid/limited_area.py
mgrid/mesh.py
mgrid/plotting.py
mgrid/regions.py
mgrid-0.1.0.dist-info/licenses/LICENSE
mgrid-0.1.0.dist-info/METADATA
mgrid-0.1.0.dist-info/WHEEL
mgrid-0.1.0.dist-info/entry_points.txt
mgrid-0.1.0.dist-info/top_level.txt
mgrid-0.1.0.dist-info/RECORD
