Metadata-Version: 2.4
Name: mgrid
Version: 0.1.0
Summary: Variable-resolution mesh generation for MPAS-based atmospheric models (MPAS, MONAN)
Author: MONAN Development Team
Author-email: "Pedro S. Peixoto" <ppeixoto@usp.br>
Maintainer: MONAN Development Team
License: MIT
Project-URL: Homepage, https://github.com/otaviomf123/mgrid
Project-URL: Documentation, https://mgrid.readthedocs.io
Project-URL: Repository, https://github.com/otaviomf123/mgrid.git
Project-URL: Issues, https://github.com/otaviomf123/mgrid/issues
Project-URL: Changelog, https://github.com/otaviomf123/mgrid/blob/main/CHANGELOG.md
Keywords: mpas,monan,atmospheric-modeling,mesh-generation,voronoi,icosahedral,spherical-grid,weather,climate,variable-resolution,jigsaw,metis
Classifier: Development Status :: 4 - Beta
Classifier: Intended Audience :: Science/Research
Classifier: License :: OSI Approved :: MIT License
Classifier: Operating System :: OS Independent
Classifier: Programming Language :: Python :: 3
Classifier: Programming Language :: Python :: 3.8
Classifier: Programming Language :: Python :: 3.9
Classifier: Programming Language :: Python :: 3.10
Classifier: Programming Language :: Python :: 3.11
Classifier: Programming Language :: Python :: 3.12
Classifier: Topic :: Scientific/Engineering :: Atmospheric Science
Classifier: Topic :: Scientific/Engineering :: GIS
Requires-Python: >=3.8
License-File: LICENSE
Requires-Dist: numpy>=1.20.0
Provides-Extra: full
Requires-Dist: shapely>=1.8.0; extra == "full"
Requires-Dist: matplotlib>=3.4.0; extra == "full"
Requires-Dist: xarray>=0.19.0; extra == "full"
Requires-Dist: netCDF4>=1.5.0; extra == "full"
Requires-Dist: scipy>=1.7.0; extra == "full"
Requires-Dist: pyproj>=3.0.0; extra == "full"
Provides-Extra: geo
Requires-Dist: shapely>=1.8.0; extra == "geo"
Requires-Dist: pyproj>=3.0.0; extra == "geo"
Requires-Dist: geopandas>=0.10.0; extra == "geo"
Provides-Extra: viz
Requires-Dist: matplotlib>=3.4.0; extra == "viz"
Requires-Dist: cartopy>=0.20.0; extra == "viz"
Provides-Extra: dev
Requires-Dist: pytest>=7.0.0; extra == "dev"
Requires-Dist: pytest-cov>=4.0.0; extra == "dev"
Requires-Dist: black>=22.0.0; extra == "dev"
Requires-Dist: isort>=5.10.0; extra == "dev"
Requires-Dist: mypy>=0.950; extra == "dev"
Requires-Dist: flake8>=4.0.0; extra == "dev"
Provides-Extra: docs
Requires-Dist: sphinx>=4.0.0; extra == "docs"
Requires-Dist: sphinx-rtd-theme>=1.0.0; extra == "docs"
Requires-Dist: numpydoc>=1.2.0; extra == "docs"
Dynamic: license-file
